ipython_markdown_inspector/__init__.py
ipython_markdown_inspector/formatter.py
ipython_markdown_inspector/models.py
ipython_markdown_inspector/tests/test_as_markdown.py
ipython_markdown_inspector-1.0.0.dist-info/METADATA
ipython_markdown_inspector-1.0.0.dist-info/WHEEL
ipython_markdown_inspector-1.0.0.dist-info/licenses/LICENSE
ipython_markdown_inspector-1.0.0.dist-info/RECORD
