Metadata-Version: 2.1
Name: ipython-markdown-inspector
Version: 1.0.0
Project-URL: Repository, https://github.com/ipython-contrib/ipython-markdown-inspector.git
Project-URL: Bug Tracker, https://github.com/ipython-contrib/ipython-markdown-inspector/issues
Author: Michał Krassowski
License: BSD 3-Clause License
License-File: LICENSE
Keywords: IPython,docstring,inpsector,markdown
Classifier: Development Status :: 4 - Beta
Classifier: Framework :: IPython
Classifier: Framework :: Jupyter
Classifier: Intended Audience :: Developers
Classifier: Intended Audience :: Science/Research
Classifier: License :: OSI Approved :: BSD License
Classifier: Programming Language :: Python
Classifier: Programming Language :: Python :: 3
Classifier: Programming Language :: Python :: 3 :: Only
Requires-Python: >=3.10
Requires-Dist: docstring-to-markdown<1.0.0,>=0.15.0
Requires-Dist: ipython>=8.22.0
Provides-Extra: dev
Requires-Dist: build; extra == 'dev'
Requires-Dist: pre-commit; extra == 'dev'
Requires-Dist: ruff==0.2.0; extra == 'dev'
Provides-Extra: test
Requires-Dist: mypy; extra == 'test'
Requires-Dist: pytest; extra == 'test'
